eml/__init__.py
eml/change_pass.py
eml/config.py
eml/delete.py
eml/detail.py
eml/init.py
eml/kill.py
eml/list.py
eml/submit.py
eml/defjob/__init__.py
eml/defjob/run.py
eml/defjob/run_changepass.py
eml/defjob/run_docker.py
eml/utils/__init__.py
eml/utils/checksum.py
eml/utils/configs.py
eml/utils/storage.py
eml_scheduler-0.0.2.data/scripts/eml-change-pass
eml_scheduler-0.0.2.data/scripts/eml-delete
eml_scheduler-0.0.2.data/scripts/eml-details
eml_scheduler-0.0.2.data/scripts/eml-init
eml_scheduler-0.0.2.data/scripts/eml-jobfile
eml_scheduler-0.0.2.data/scripts/eml-kill
eml_scheduler-0.0.2.data/scripts/eml-list
eml_scheduler-0.0.2.data/scripts/eml-submit
eml_scheduler-0.0.2.dist-info/LICENSE
eml_scheduler-0.0.2.dist-info/METADATA
eml_scheduler-0.0.2.dist-info/WHEEL
eml_scheduler-0.0.2.dist-info/top_level.txt
eml_scheduler-0.0.2.dist-info/RECORD
